aptManager/AptManager.py
aptManager/__init__.py
aptManager/aptManager.py
aptManager-0.2.8.data/scripts/aptManager
aptManager-0.2.8.data/scripts/main
aptManager-0.2.8.dist-info/METADATA
aptManager-0.2.8.dist-info/WHEEL
aptManager-0.2.8.dist-info/top_level.txt
aptManager-0.2.8.dist-info/RECORD
